pathlib_next/__init__.py
pathlib_next/fspath.py
pathlib_next/mempath.py
pathlib_next/path.py
pathlib_next/protocols/__init__.py
pathlib_next/protocols/fs.py
pathlib_next/protocols/io.py
pathlib_next/uri/__init__.py
pathlib_next/uri/query.py
pathlib_next/uri/source.py
pathlib_next/uri/schemes/__init__.py
pathlib_next/uri/schemes/file.py
pathlib_next/uri/schemes/http.py
pathlib_next/uri/schemes/sftp.py
pathlib_next/utils/__init__.py
pathlib_next/utils/glob.py
pathlib_next/utils/stat.py
pathlib_next/utils/sync.py
pathlib_next-0.3.5.dist-info/METADATA
pathlib_next-0.3.5.dist-info/WHEEL
pathlib_next-0.3.5.dist-info/licenses/LICENSE
pathlib_next-0.3.5.dist-info/RECORD
